crewai_mcp_toolbox/__init__.py
crewai_mcp_toolbox/client.py
crewai_mcp_toolbox/exceptions.py
crewai_mcp_toolbox/factory.py
crewai_mcp_toolbox/utils.py
crewai_mcp_toolbox/worker.py
crewai_mcp_toolbox-0.1.0.dist-info/METADATA
crewai_mcp_toolbox-0.1.0.dist-info/WHEEL
crewai_mcp_toolbox-0.1.0.dist-info/licenses/LICENSE
crewai_mcp_toolbox-0.1.0.dist-info/RECORD
