Metadata-Version: 2.4
Name: crewai-mcp-toolbox
Version: 0.1.0
Summary: CrewAI integration for the Model Context Protocol (MCP)
Project-URL: Homepage, https://github.com/openbridge/mcp-toolbox
Project-URL: Bug Tracker, https://github.com/openbridge/mcp-toolbox/issues
Author: MCP Toolbox Authors
License: MIT License
License-File: LICENSE
Classifier: Development Status :: 3 - Alpha
Classifier: Intended Audience :: Developers
Classifier: License :: OSI Approved :: MIT License
Classifier: Programming Language :: Python :: 3
Classifier: Programming Language :: Python :: 3.9
Classifier: Programming Language :: Python :: 3.10
Classifier: Programming Language :: Python :: 3.11
Classifier: Programming Language :: Python :: 3.12
Requires-Python: >=3.9
Requires-Dist: crewai-tools>=0.1.0
Requires-Dist: crewai>=0.28.0
Requires-Dist: mcp-python-client>=0.1.0
Requires-Dist: modelcontextprotocol>=0.1.0
Requires-Dist: pydantic>=2.0.0
Provides-Extra: dev
Requires-Dist: black>=23.0.0; extra == 'dev'
Requires-Dist: flake8>=6.0.0; extra == 'dev'
Requires-Dist: isort>=5.12.0; extra == 'dev'
Requires-Dist: mypy>=1.0.0; extra == 'dev'
Requires-Dist: pytest-asyncio>=0.23.0; extra == 'dev'
Requires-Dist: pytest>=7.0.0; extra == 'dev'
Provides-Extra: test
Requires-Dist: pytest-asyncio>=0.23.0; extra == 'test'
Requires-Dist: pytest>=7.0.0; extra == 'test'
